hyperkneefinder/__init__.py
hyperkneefinder/hyperkneefinder.py
HyperkneeFinder-0.0.3.dist-info/LICENSE
HyperkneeFinder-0.0.3.dist-info/METADATA
HyperkneeFinder-0.0.3.dist-info/WHEEL
HyperkneeFinder-0.0.3.dist-info/top_level.txt
HyperkneeFinder-0.0.3.dist-info/RECORD
