Metadata-Version: 2.1
Name: HyperkneeFinder
Version: 0.0.3
Summary: A tool for optimizing two inter-dependent parameters.
Home-page: https://github.com/vlavorini/hyperknee_finder
Author: Vincenzo Lavorini
Author-email: vincenzo.lavorini@protonmail.ch
Classifier: Development Status :: 3 - Alpha
Classifier: Intended Audience :: Science/Research
Classifier: License :: OSI Approved :: BSD License
Classifier: Operating System :: POSIX :: Linux
Classifier: Programming Language :: Python :: 3
Classifier: Programming Language :: Python :: 3.9
Classifier: Programming Language :: Python :: 3.10
License-File: LICENSE
Requires-Dist: numpy
Requires-Dist: matplotlib
Requires-Dist: scikit-learn
